kiwoom-1.5.0.dist-info/METADATA
kiwoom-1.5.0.dist-info/WHEEL
kiwoom-1.5.0.dist-info/entry_points.txt
kiwoom-1.5.0.dist-info/licenses/LICENSE
kiwoom/__init__.py
kiwoom/__version__.py
kiwoom/config/__init__.py
kiwoom/config/const.py
kiwoom/config/error.py
kiwoom/config/general.py
kiwoom/config/history.py
kiwoom/config/screen.py
kiwoom/config/types.py
kiwoom/core/__init__.py
kiwoom/core/bot.py
kiwoom/core/connector.py
kiwoom/core/kiwoom.py
kiwoom/core/server.py
kiwoom/data/__init__.py
kiwoom/data/preps.py
kiwoom/data/share.py
kiwoom/utils/__init__.py
kiwoom/utils/general.py
kiwoom/utils/manager.py
kiwoom/wrapper/__init__.py
kiwoom/wrapper/api.py
kiwoom-1.5.0.dist-info/RECORD
