Metadata-Version: 2.4
Name: kiwoom
Version: 1.5.0
Summary: Simple Python Wrapper for Kiwoom Open API+ (Stable)
Keywords: Kiwoom,Heroes,Open API+,키움증권,영웅문,System Trading,Algorithmic Trading
Author-Email: breadum <breadum.kr@gmail.com>
License-Expression: MIT
Classifier: Topic :: Office/Business :: Financial :: Investment
Classifier: Development Status :: 3 - Alpha
Classifier: Operating System :: Microsoft :: Windows
Classifier: Environment :: Win32 (MS Windows)
Classifier: Programming Language :: Python
Classifier: Programming Language :: Python :: 3.8
Classifier: Programming Language :: Python :: 3.9
Classifier: Programming Language :: Python :: 3.10
Classifier: Programming Language :: Python :: 3.11
Project-URL: Homepage, https://github.com/breadum/kiwoom
Project-URL: Tutorials, https://github.com/breadum/kiwoom/tree/main/tutorials
Project-URL: Documentation, https://github.com/breadum/kiwoom/blob/main/README.md
Project-URL: Repository, https://github.com/breadum/kiwoom
Project-URL: Download,  https://pypi.org/project/kiwoom
Project-URL: Issues, https://github.com/breadum/kiwoom/issues
Requires-Python: <3.12,>=3.8
Requires-Dist: pyqt5-qt5==5.15.2; sys_platform == "win32" and python_version == "3.11.*"
Requires-Dist: PyQt5>=5.15.9; sys_platform == "win32"
Requires-Dist: numpy<2,>=1.2; sys_platform == "win32"
Requires-Dist: pandas<2; sys_platform == "win32"
Requires-Dist: tabulate>=0.9
